goblinfish/metrics/process_timing.py
goblinfish_metrics_process_timing-0.0.3.dist-info/LICENSE
goblinfish_metrics_process_timing-0.0.3.dist-info/METADATA
goblinfish_metrics_process_timing-0.0.3.dist-info/WHEEL
goblinfish_metrics_process_timing-0.0.3.dist-info/top_level.txt
goblinfish_metrics_process_timing-0.0.3.dist-info/RECORD
