Metadata-Version: 2.2
Name: goblinfish-metrics-process_timing
Version: 0.0.3
Summary: Context-managed metrics tracking and output, including but not limited to process/subprocess latencies.
Author-email: Brian Allbee <brian.allbee+goblinfish.process_timing+@gmail.com>
Maintainer-email: Brian Allbee <brian.allbee+goblinfish.process_timing+@gmail.com>
License: MIT License
Keywords: aws,cloudwatch,log,metrics,process timing
Classifier: Programming Language :: Python :: 3.13
Classifier: Programming Language :: Python :: 3.12
Classifier: Programming Language :: Python :: 3.11
Classifier: Programming Language :: Python :: 3
Classifier: Development Status :: 4 - Beta
Classifier: Intended Audience :: Developers
Classifier: License :: OSI Approved :: MIT License
Classifier: Natural Language :: English
Classifier: Operating System :: OS Independent
Classifier: Topic :: System :: Logging
Classifier: Topic :: System :: Monitoring
Requires-Python: >=3.11
License-File: LICENSE
